{
  "name": "MatrixSvgRenderOptions",
  "fullName": "CodeGlyphX.Rendering.Svg.MatrixSvgRenderOptions",
  "namespace": "CodeGlyphX.Rendering.Svg",
  "kind": "Class",
  "slug": "codeglyphx-rendering-svg-matrixsvgrenderoptions",
  "summary": "Options for rendering generic 2D matrices to SVG.",
  "remarks": null,
  "methods": [
    {
      "name": "WithModuleSize",
      "summary": "Sets the module size in pixels.",
      "returns": null,
      "parameters": [
        {
          "name": "size",
          "type": "System.Int32",
          "summary": null
        }
      ]
    },
    {
      "name": "WithQuietZone",
      "summary": "Sets the quiet zone size in modules.",
      "returns": null,
      "parameters": [
        {
          "name": "quietZone",
          "type": "System.Int32",
          "summary": null
        }
      ]
    },
    {
      "name": "WithDarkColor",
      "summary": "Sets the dark color (CSS value).",
      "returns": null,
      "parameters": [
        {
          "name": "color",
          "type": "System.String",
          "summary": null
        }
      ]
    },
    {
      "name": "WithLightColor",
      "summary": "Sets the light color (CSS value).",
      "returns": null,
      "parameters": [
        {
          "name": "color",
          "type": "System.String",
          "summary": null
        }
      ]
    }
  ],
  "properties": [
    {
      "name": "ModuleSize",
      "summary": "Module size in pixels."
    },
    {
      "name": "QuietZone",
      "summary": "Quiet zone size in modules."
    },
    {
      "name": "DarkColor",
      "summary": "Foreground color (CSS)."
    },
    {
      "name": "LightColor",
      "summary": "Background color (CSS)."
    }
  ],
  "fields": [],
  "events": []
}